xchainpy2_litecoin/__init__.py
xchainpy2_litecoin/const.py
xchainpy2_litecoin/ltc_client.py
xchainpy2_litecoin/utils.py
xchainpy2_litecoin-0.0.9.dist-info/LICENSE
xchainpy2_litecoin-0.0.9.dist-info/METADATA
xchainpy2_litecoin-0.0.9.dist-info/WHEEL
xchainpy2_litecoin-0.0.9.dist-info/top_level.txt
xchainpy2_litecoin-0.0.9.dist-info/RECORD
